mixins/__init__.py
mixins/crud_api_test_mixin.py
mixins/response_structure_mixin.py
mixins/validation_error_test_mixin.py
drf_universal_api_test_mixins-0.1.1.dist-info/LICENSE
drf_universal_api_test_mixins-0.1.1.dist-info/METADATA
drf_universal_api_test_mixins-0.1.1.dist-info/WHEEL
drf_universal_api_test_mixins-0.1.1.dist-info/RECORD
