Metadata-Version: 2.3
Name: drf-universal-api-test-mixins
Version: 0.1.1
Summary: Универсальные миксины для тестирования DRF API
License: MIT
Author: Eduard Slobodyanik
Author-email: slobodyanik.ed@gmail.com
Requires-Python: >=3.12,<4.0
Classifier: License :: OSI Approved :: MIT License
Classifier: Programming Language :: Python :: 3
Classifier: Programming Language :: Python :: 3.12
Classifier: Programming Language :: Python :: 3.13
Requires-Dist: django (>=5.2.4,<6.0.0)
Requires-Dist: djangorestframework (>=3.16.0,<4.0.0)
